simplelib5.py
simplelib5-0.1.0.dist-info/METADATA
simplelib5-0.1.0.dist-info/WHEEL
simplelib5-0.1.0.dist-info/top_level.txt
simplelib5-0.1.0.dist-info/RECORD
